folder/FloatingNormalizer.v
module Stage4_Normalize (
  input  wire        clk,
  input  wire        rst,
  input  wire [24:0] sum_man,
  input  wire [7:0]  exp_in,
  input  wire        sum_sign,

  output reg  [31:0] result
);
  // leading-zero count

  
  reg [7:0]  exp_adj;
  reg [23:0] norm_man;
  reg [4:0]  shift;

  function integer leading_zeros;
    input [23:0] val;
    integer i;
    begin
      leading_zeros = 0;
      for (i = 23; i >= 0; i = i - 1) begin
        if (val[i] == 1'b1) begin
          leading_zeros = 23 - i;
          i = -1; // exit loop manually
        end
      end
    end
  endfunction

  always @(posedge clk or posedge rst) begin
    if (rst) begin
      result <= 0;
    end else begin
      if (sum_man[24]) begin
        // overflow from addition
        exp_adj   = exp_in + 1;
        norm_man  = sum_man[24:1];
      end else begin
        shift     = leading_zeros(sum_man[23:0]);
        exp_adj   = exp_in - shift;
        norm_man  = sum_man[23:0] << shift;
      end
      result <= { sum_sign, exp_adj, norm_man[22:0] };
    end
  end
endmodule

folder/FloatingAdder.v
// ================================
// Stage3_Adder (updated to take B_sign_eff)
// ================================
module Stage3_Adder (
  input  wire        clk,
  input  wire        rst,
  input  wire [23:0] A_man_aligned,
  input  wire [23:0] B_man_aligned,
  input  wire        A_sign,
  input  wire        B_sign_eff,   // <-- now using the effective B sign

  output reg  [24:0] sum_man,
  output reg         sum_sign
);
  wire same_sign = (A_sign == B_sign_eff);
  reg  [24:0] temp_result; // Bit 24 is an overflow bit (set if the addition produced a carry out of the 24-bit mantissa).

  always @(posedge clk or posedge rst) begin
    if (rst) begin
      sum_man  <= 0;
      sum_sign <= 0;
    end else begin
      if (same_sign) begin
        // Perform addition
        temp_result <= A_man_aligned + B_man_aligned;
        sum_sign <= A_sign;  // Both signs are the same
      end else begin
        // Perform subtraction: larger - smaller
        if (A_man_aligned >= B_man_aligned) begin
          temp_result <= A_man_aligned - B_man_aligned;
          sum_sign <= A_sign;  // A is larger → A's sign
        end else begin
          temp_result <= B_man_aligned - A_man_aligned;
          sum_sign <= B_sign_eff;  // B is larger → B's sign
        end
      end

      sum_man <= temp_result;
    end
  end
endmodule

folder/FloatingAllign.v
module Stage2_Align (
  input  wire        clk,
  input  wire        rst,
  input  wire [23:0] A_man,
  input  wire [23:0] B_man,
  input  wire [7:0]  exp_diff,
  input  wire        A_bigger,
  input  wire [7:0]  A_exp,
  input  wire [7:0]  B_exp,

  output reg  [23:0] A_man_aligned,
  output reg  [23:0] B_man_aligned,
  output reg  [7:0]  exp_out
);
  always @(posedge clk or posedge rst) begin
    if (rst) begin
      {A_man_aligned,B_man_aligned,exp_out} <= 0;
    end else if (A_bigger) begin
      A_man_aligned <= A_man;
      B_man_aligned <= B_man >> exp_diff;
      exp_out       <= A_exp;
    end else begin
      A_man_aligned <= A_man >> exp_diff;
      B_man_aligned <= B_man;
      exp_out       <= B_exp;
    end
  end
endmodule

folder/FloatingDetection.v
module Stage1_5_SpecialCase (
  input  wire        clk,
  input  wire        rst,

  // Inputs from Stage 1
  input  wire        sign_A,
  input  wire        sign_B_eff,
  input  wire [7:0]  exp_A,
  input  wire [7:0]  exp_B,
  input  wire [23:0] man_A,       // includes implicit leading bit
  input  wire [23:0] man_B,
  input  wire [7:0]  exp_diff,
  input  wire        A_is_bigger,
  input  wire        operation,   // for tie-breaking zeros

  // Bypass outputs
  output reg         bypass,        // '1' if we're shortcutting
  output reg  [31:0] bypass_result, // final IEEE-754 word

  // Otherwise pass through to Stage 2
  output reg         sign_A_out,
  output reg         sign_B_out,
  output reg  [7:0]  exp_A_out,
  output reg  [7:0]  exp_B_out,
  output reg  [23:0] man_A_out,
  output reg  [23:0] man_B_out,
  output reg  [7:0]  exp_diff_out,
  output reg         A_is_bigger_out
);

  // helper wires
  wire A_zero = (exp_A == 8'd0    && man_A[22:0] == 0); // if the exponent and mantis of A all are zeroes (sign doesn't matter)
  wire B_zero = (exp_B == 8'd0    && man_B[22:0] == 0); 
  wire A_inf  = (exp_A == 8'hFF   && man_A[22:0] == 0); // if exponent is all ones and mantis is all zeroes
  wire B_inf  = (exp_B == 8'hFF   && man_B[22:0] == 0);
  wire A_nan  = (exp_A == 8'hFF   && man_A[22:0] != 0); // if exponent is all ones and mantis is non-zero's (sign doesn't matter)
  wire B_nan  = (exp_B == 8'hFF   && man_B[22:0] != 0);

  always @(posedge clk or posedge rst) begin
    if (rst) begin
      bypass         <= 1'b0;
      bypass_result  <= 32'd0;
      // clear pass-through regs
      {sign_A_out, sign_B_out, exp_A_out, exp_B_out, man_A_out, man_B_out, exp_diff_out, A_is_bigger_out}
                     <= 0;
    end else begin
      // Default: no bypass; propagate inputs
      bypass            <= 1'b0;
      sign_A_out        <= sign_A;
      sign_B_out        <= sign_B_eff;
      exp_A_out         <= exp_A;
      exp_B_out         <= exp_B;
      man_A_out         <= man_A;
      man_B_out         <= man_B;
      exp_diff_out      <= exp_diff;
      A_is_bigger_out   <= A_is_bigger;

      // 1) NaN rules: if either is NaN → quiet NaN
      if (A_nan || B_nan) begin
        bypass        <= 1'b1;
        // propagate the payload of the first NaN you see
        bypass_result <= A_nan ? {sign_A, 8'b1, man_A[22:0]} 
                               : {sign_B_eff, 8'b1, man_B[22:0]};
      end
      // 2) Infinity rules
      else if (A_inf || B_inf) begin
        bypass       <= 1'b1;
        if (A_inf && B_inf) begin
          // ∞ - ∞ = NaN, ∞ + ∞ = sign_A ? -Inf : +Inf
          if (operation && (sign_A ^ sign_B_eff)) begin // op AND signs difference
            bypass_result <= 32'h7FC00000; // quiet NaN
          end else begin
            bypass_result <= { sign_A, 8'b1, 23'b0 };
          end
        end else if (A_inf) begin
          bypass_result <= { sign_A, 8'b1, 23'b0 };
        end else begin
          bypass_result <= { sign_B_eff, 8'b1, 23'b0 };
        end
      end
      // 3) Zero rules
      else if (A_zero || B_zero) begin
        bypass       <= 1'b1;
        // A==0, B==0 → result signed-zero (sign = op? sign_A^1 : sign_A)
        if (A_zero && B_zero) begin
          bypass_result <= {(operation ? {sign_A ^ 1'b1} : {sign_A}) , 8'b0, 23'b0 };
        end
        // one of them is zero → just return the other
        else if (A_zero) begin
          bypass_result <= { sign_B_eff, exp_B, man_B[22:0] };
        end else begin
          bypass_result <= { sign_A, exp_A, man_A[22:0] };
        end
      end
      // else: no special case → go down main path
    end
  end

endmodule
//test again

folder/FloatingCompare.v
// ================================
// Stage1_Compare (updated)
// ================================
module Stage1_Compare (
  input  wire         clk,
  input  wire         rst,
  input  wire [31:0]  A,
  input  wire [31:0]  B,
  input  wire         operation,   // 0→add, 1→subtract

  output reg          A_sign,
  output reg          B_sign,
  output reg          B_sign_eff,  // <-- effective B sign
  output reg  [7:0]   A_exp,
  output reg  [7:0]   B_exp,
  output reg  [23:0]  A_man,
  output reg  [23:0]  B_man,
  output reg  [7:0]   exp_diff,
  output reg          A_bigger
);
  always @(posedge clk or posedge rst) begin
    if (rst) begin
      {A_sign,B_sign_eff,A_exp,B_exp,A_man,B_man,exp_diff,A_bigger} <= 0;
    end else begin
      
      // raw extraction
      A_sign <= A[31];
      B_sign <= B[31];
      B_sign_eff <= B_sign ^ operation;  // A - B = A + (-B)
;   // <-- XOR in the operation bit
      A_exp  <= A[30:23];
      B_exp  <= B[30:23];
      // build mantissas
      A_man  <= (A[30:23]==0) ? {1'b0, A[22:0]} : {1'b1, A[22:0]}; //implicit leading 1 for normalized , 0 for denormalized
      B_man  <= (B[30:23]==0) ? {1'b0, B[22:0]} : {1'b1, B[22:0]};
      // exponent diff and bigger flag
      if (A[30:23] >= B[30:23]) begin
        exp_diff  <= A[30:23] - B[30:23];
        A_bigger  <= 1;
      end else begin
        exp_diff  <= B[30:23] - A[30:23];
        A_bigger  <= 0;
      end
    end
  end
endmodule

folder/PipelinedFAdd.v
module PipelinedFAdd (
  input  wire        clk,
  input  wire        rst,
  input  wire [31:0] A,
  input  wire [31:0] B,
  input  wire        operation,

  output wire [31:0] result
);

  // Stage 1 outputs
  wire        A_sign1, B_sign1_eff, A_bigger1;
  wire [7:0]  A_exp1, B_exp1, diff1;
  wire [23:0] A_man1, B_man1;

  Stage1_Compare U1 (
    .clk(clk),
    .rst(rst),
    .A(A),
    .B(B),
    .operation(operation),
    .A_sign(A_sign1),
    .B_sign_eff(B_sign1_eff),
    .A_exp(A_exp1),
    .B_exp(B_exp1),
    .A_man(A_man1),
    .B_man(B_man1),
    .exp_diff(diff1),
    .A_bigger(A_bigger1)
  );

  // Stage 1.5 (Special Case Handler)
  wire        bypass_1_5;
  wire [31:0] bypass_res;
  wire        sA2, sB2, A_big2;
  wire [7:0]  eA2, eB2, diff2;
  wire [23:0] mA2, mB2;

  Stage1_5_SpecialCase U1_5 (
    .clk(clk),
    .rst(rst),
    .sign_A(A_sign1),
    .sign_B_eff(B_sign1_eff),
    .exp_A(A_exp1),
    .exp_B(B_exp1),
    .man_A(A_man1),
    .man_B(B_man1),
    .exp_diff(diff1),
    .A_is_bigger(A_bigger1),
    .operation(operation),
    .bypass(bypass_1_5),
    .bypass_result(bypass_res),
    .sign_A_out(sA2),
    .sign_B_out(sB2),
    .exp_A_out(eA2),
    .exp_B_out(eB2),
    .man_A_out(mA2),
    .man_B_out(mB2),
    .exp_diff_out(diff2),
    .A_is_bigger_out(A_big2)
  );

  // Stage 2: Align Mantissas
  wire [23:0] A_man2, B_man2;
  wire [7:0]  exp2;

  Stage2_Align U2 (
    .clk(clk),
    .rst(rst),
    .A_man(mA2),
    .B_man(mB2),
    .exp_diff(diff2),
    .A_bigger(A_big2),
    .A_exp(eA2),
    .B_exp(eB2),
    .A_man_aligned(A_man2),
    .B_man_aligned(B_man2),
    .exp_out(exp2)
  );

  // Stage 3: Add/Subtract
  wire [24:0] sum3;
  wire        sum_sign3;

  Stage3_Adder U3 (
    .clk(clk),
    .rst(rst),
    .A_man_aligned(A_man2),
    .B_man_aligned(B_man2),
    .A_sign(sA2),
    .B_sign_eff(sB2),
    .sum_man(sum3),
    .sum_sign(sum_sign3)
  );

  // Stage 4: Normalize
  wire [31:0] result_stage4;

  Stage4_Normalize U4 (
    .clk(clk),
    .rst(rst),
    .sum_man(sum3),
    .exp_in(exp2),
    .sum_sign(sum_sign3),
    .result(result_stage4)
  );

  // Final result logic: check bypass
  assign result = bypass_1_5 ? bypass_res : result_stage4;

endmodule

folder/tb_PipelinedFAdd.v
`timescale 1ns/1ps

module tb_PipelinedFAdd();

    reg clk = 0;
    reg reset = 1;
    reg [31:0] A, B;
    reg operation; // 0: Add, 1: Sub

    wire [31:0] result;

    PipelinedFAdd dut (
        .clk(clk),
        .rst(rst),
        .A(A),
        .B(B),
        .operation(operation),
        .result(result)
    );

    // Clock generation
    always #5 clk = ~clk;

        initial begin

            $monitor("Time: %0t | A: %h | B: %h | Op: %b | Result: %h", $time, A, B, operation, result);
            $dumpfile("build/waveform.vcd");
            $dumpvars(0, tb_PipelinedFAdd);
            

        #10 reset = 0;

        // // Test 1: 13.65 + 10.2555 = 23.9055
        // A = 32'h415a6666; // 13.65
        // B = 32'h41241687; // 10.2555
        // operation = 0;
        // #50;

        // // Test 2: 13.65 - 10.2555 = 3.3945
        // A = 32'h415a6666; // 13.65
        // B = 32'h41241687; // 10.2555
        // operation = 1;
        // #50;
        // //Test 3: -13.65 + 10.2555 = -3.3945
        // A = 32'hc15a6666; // -13.65
        // B = 32'h41241687; // 10.2555
        // operation = 0;
        // #50;
        // // Test 4: -13.65 - 10.2555 = -23.9055
        // A = 32'hc15a6666; // -13.65
        // B = 32'h41241687; // 10.2555
        // operation = 1;
        // #50;

        A = 32'h7F800000;
        B = 32'hFF800000;
        operation = 0;
        #50;

        $finish;
    end

endmodule

build/waveform.vcd
$date
	Mon Jun  9 15:27:53 2025
$end
$version
	Icarus Verilog
$end
$timescale
	1ps
$end
$scope module tb_PipelinedFAdd $end
$var wire 1 ! rst $end
$var wire 32 " result [31:0] $end
$var reg 32 # A [31:0] $end
$var reg 32 $ B [31:0] $end
$var reg 1 % clk $end
$var reg 1 & operation $end
$var reg 1 ' reset $end
$scope module dut $end
$var wire 32 ( A [31:0] $end
$var wire 32 ) B [31:0] $end
$var wire 1 % clk $end
$var wire 1 & operation $end
$var wire 1 ! rst $end
$var wire 1 * sum_sign3 $end
$var wire 25 + sum3 [24:0] $end
$var wire 1 , sB2 $end
$var wire 1 - sA2 $end
$var wire 32 . result_stage4 [31:0] $end
$var wire 32 / result [31:0] $end
$var wire 24 0 mB2 [23:0] $end
$var wire 24 1 mA2 [23:0] $end
$var wire 8 2 exp2 [7:0] $end
$var wire 8 3 eB2 [7:0] $end
$var wire 8 4 eA2 [7:0] $end
$var wire 8 5 diff2 [7:0] $end
$var wire 8 6 diff1 [7:0] $end
$var wire 32 7 bypass_res [31:0] $end
$var wire 1 8 bypass_1_5 $end
$var wire 1 9 B_sign1_eff $end
$var wire 24 : B_man2 [23:0] $end
$var wire 24 ; B_man1 [23:0] $end
$var wire 8 < B_exp1 [7:0] $end
$var wire 1 = A_sign1 $end
$var wire 24 > A_man2 [23:0] $end
$var wire 24 ? A_man1 [23:0] $end
$var wire 8 @ A_exp1 [7:0] $end
$var wire 1 A A_bigger1 $end
$var wire 1 B A_big2 $end
$scope module U1 $end
$var wire 32 C A [31:0] $end
$var wire 32 D B [31:0] $end
$var wire 1 % clk $end
$var wire 1 & operation $end
$var wire 1 ! rst $end
$var reg 1 A A_bigger $end
$var reg 8 E A_exp [7:0] $end
$var reg 24 F A_man [23:0] $end
$var reg 1 = A_sign $end
$var reg 8 G B_exp [7:0] $end
$var reg 24 H B_man [23:0] $end
$var reg 1 I B_sign $end
$var reg 1 9 B_sign_eff $end
$var reg 8 J exp_diff [7:0] $end
$upscope $end
$scope module U1_5 $end
$var wire 1 K A_inf $end
$var wire 1 A A_is_bigger $end
$var wire 1 L A_nan $end
$var wire 1 M A_zero $end
$var wire 1 N B_inf $end
$var wire 1 O B_nan $end
$var wire 1 P B_zero $end
$var wire 1 % clk $end
$var wire 8 Q exp_A [7:0] $end
$var wire 8 R exp_B [7:0] $end
$var wire 8 S exp_diff [7:0] $end
$var wire 24 T man_A [23:0] $end
$var wire 24 U man_B [23:0] $end
$var wire 1 & operation $end
$var wire 1 ! rst $end
$var wire 1 = sign_A $end
$var wire 1 9 sign_B_eff $end
$var reg 1 B A_is_bigger_out $end
$var reg 1 8 bypass $end
$var reg 32 V bypass_result [31:0] $end
$var reg 8 W exp_A_out [7:0] $end
$var reg 8 X exp_B_out [7:0] $end
$var reg 8 Y exp_diff_out [7:0] $end
$var reg 24 Z man_A_out [23:0] $end
$var reg 24 [ man_B_out [23:0] $end
$var reg 1 - sign_A_out $end
$var reg 1 , sign_B_out $end
$upscope $end
$scope module U2 $end
$var wire 1 B A_bigger $end
$var wire 8 \ A_exp [7:0] $end
$var wire 24 ] A_man [23:0] $end
$var wire 8 ^ B_exp [7:0] $end
$var wire 24 _ B_man [23:0] $end
$var wire 1 % clk $end
$var wire 8 ` exp_diff [7:0] $end
$var wire 1 ! rst $end
$var reg 24 a A_man_aligned [23:0] $end
$var reg 24 b B_man_aligned [23:0] $end
$var reg 8 c exp_out [7:0] $end
$upscope $end
$scope module U3 $end
$var wire 24 d A_man_aligned [23:0] $end
$var wire 1 - A_sign $end
$var wire 24 e B_man_aligned [23:0] $end
$var wire 1 , B_sign_eff $end
$var wire 1 % clk $end
$var wire 1 ! rst $end
$var wire 1 f same_sign $end
$var reg 25 g sum_man [24:0] $end
$var reg 1 * sum_sign $end
$var reg 25 h temp_result [24:0] $end
$upscope $end
$scope module U4 $end
$var wire 1 % clk $end
$var wire 8 i exp_in [7:0] $end
$var wire 1 ! rst $end
$var wire 25 j sum_man [24:0] $end
$var wire 1 * sum_sign $end
$var reg 8 k exp_adj [7:0] $end
$var reg 24 l norm_man [23:0] $end
$var reg 32 m result [31:0] $end
$var reg 5 n shift [4:0] $end
$scope function leading_zeros $end
$var reg 24 o val [23:0] $end
$var integer 32 p i [31:0] $end
$upscope $end
$upscope $end
$upscope $end
$upscope $end
$enddefinitions $end
#0
$dumpvars
bx p
bx o
bx n
bx m
bx l
bx k
bx j
bx i
bx h
bx g
xf
bx e
bx d
bx c
bx b
bx a
bx `
bx _
bx ^
bx ]
bx \
bx [
bx Z
bx Y
bx X
bx W
bx V
bx U
bx T
bx S
bx R
bx Q
xP
xO
xN
xM
xL
xK
bx J
xI
bx H
bx G
bx F
bx E
bx D
bx C
xB
xA
bx @
bx ?
bx >
x=
bx <
bx ;
bx :
x9
x8
bx 7
bx 6
bx 5
bx 4
bx 3
bx 2
bx 1
bx 0
bx /
bx .
x-
x,
bx +
x*
bx )
bx (
1'
x&
0%
bx $
bx #
bx "
z!
$end
#5000
0A
08
b0 n
b11111111111111111111111111111111 p
1%
#10000
0%
0&
b11111111100000000000000000000000 $
b11111111100000000000000000000000 )
b11111111100000000000000000000000 D
b1111111100000000000000000000000 #
b1111111100000000000000000000000 (
b1111111100000000000000000000000 C
0'
#15000
1N
0O
1K
0L
0P
0M
0B
1A
b0 6
b0 J
b0 S
b100000000000000000000000 ;
b100000000000000000000000 H
b100000000000000000000000 U
b100000000000000000000000 ?
b100000000000000000000000 F
b100000000000000000000000 T
b11111111 <
b11111111 G
b11111111 R
b11111111 @
b11111111 E
b11111111 Q
1I
0=
b11111111111111111111111111111111 p
1%
#20000
0%
#25000
b1111111100000000000000000000000 "
b1111111100000000000000000000000 /
19
b1111111100000000000000000000000 7
b1111111100000000000000000000000 V
18
1B
b0 5
b0 Y
b0 `
b100000000000000000000000 0
b100000000000000000000000 [
b100000000000000000000000 _
b100000000000000000000000 1
b100000000000000000000000 Z
b100000000000000000000000 ]
b11111111 3
b11111111 X
b11111111 ^
b11111111 4
b11111111 W
b11111111 \
0-
b11111111111111111111111111111111 p
1%
#30000
0%
#35000
0f
b11111111 2
b11111111 c
b11111111 i
b100000000000000000000000 :
b100000000000000000000000 b
b100000000000000000000000 e
b100000000000000000000000 >
b100000000000000000000000 a
b100000000000000000000000 d
1,
18
b11111111111111111111111111111111 p
1%
#40000
0%
#45000
18
0*
b0 h
bx11111111xxxxxxxxxxxxxxxxxxxxxxx .
bx11111111xxxxxxxxxxxxxxxxxxxxxxx m
b11111111 k
b11111111111111111111111111111111 p
1%
#50000
0%
#55000
b11111111xxxxxxxxxxxxxxxxxxxxxxx .
b11111111xxxxxxxxxxxxxxxxxxxxxxx m
b0 +
b0 g
b0 j
18
b11111111111111111111111111111111 p
1%
