folder/FloatingNormalizer.v
module Stage4_Normalize (
  input  wire        clk,
  input  wire        rst,
  input  wire [24:0] sum_man, // 23 bits for mantisa 1 bit for overflow, 1 bit for sign 
  input  wire [7:0]  exp_in, // the common exponent before normalization. 8 bits
  input  wire        sum_sign,

  output reg  [31:0] result
);
  // leading-zero count

  
  reg [7:0]  exp_adj; // Adjusted exponent after normalization
  reg [23:0] norm_man;// Normalized mantissa with implicit leading 1
  reg [4:0]  shift; // Number of left shifts needed (0–23)


  // Purpose: Count how many zeros precede the first ‘1’ in the 24-bit vector val.
  // Starts at the MSB (i=23) and works down to LSB (i=0).
  /* 
    Example: val=0000_0000_0000_0000_0000_1011 → returns 20
    That means you must shift left by 20 to bring that ‘1’ into bit‐23.
  */
  function integer leading_zeros;
    input [23:0] val;
    integer i;
    begin
      leading_zeros = 0;
      for (i = 23; i >= 0; i = i - 1) begin
        if (val[i] == 1'b1) begin
          leading_zeros = 23 - i;
          i = -1; // exit loop manually
        end
      end
    end
  endfunction

  always @(posedge clk or posedge rst) begin
    if (rst) begin
      result <= 0;
    end else begin
      if (sum_man[24]) begin
        // overflow from addition
        exp_adj   = exp_in + 1;
        norm_man  = sum_man[24:1]; // shift right by 1 , can be replaced by wire assignment norm_man >> 1
      end else begin
        /*
        If no overflow, we may have a result like 0.01101... (bit 23 = 0).
          Compute shift = leading_zeros(sum_man[23:0]).
          Adjust exponent: exp_adj = exp_in − shift.
          Left-shift mantissa by shift to bring first ‘1’ into bit 23.
        */
        shift     = leading_zeros(sum_man[23:0]);
        exp_adj   = exp_in - shift;
        norm_man  = sum_man[23:0] << shift;
      end
      result <= { sum_sign, exp_adj, norm_man[22:0] };
    end
  end
endmodule

folder/FloatingAdder.v
// ================================
// Stage3_Adder (updated to take B_sign_eff)
// ================================
module Stage3_Adder (
  input  wire        clk,
  input  wire        rst,
  input  wire [23:0] A_man_aligned,
  input  wire [23:0] B_man_aligned,
  input  wire        A_sign,
  input  wire        B_sign_eff,   // <-- now using the effective B sign

  output reg  [24:0] sum_man,
  output reg         sum_sign
);
  wire same_sign = (A_sign == B_sign_eff);
  reg  [24:0] temp_result; // Bit 24 is an overflow bit (set if the addition produced a carry out of the 24-bit mantissa).

  always @(posedge clk or posedge rst) begin
    if (rst) begin
      sum_man  <= 0;
      sum_sign <= 0;
    end else begin
      if (same_sign) begin
        // Perform addition
        temp_result <= A_man_aligned + B_man_aligned;
        sum_sign <= A_sign;  // Both signs are the same
      end else begin
        // Perform subtraction: larger - smaller
        if (A_man_aligned >= B_man_aligned) begin
          temp_result <= A_man_aligned - B_man_aligned;
          sum_sign <= A_sign;  // A is larger → A's sign
        end else begin
          temp_result <= B_man_aligned - A_man_aligned;
          sum_sign <= B_sign_eff;  // B is larger → B's sign
        end
      end

      sum_man <= temp_result;
    end
  end
endmodule

folder/FloatingAllign.v
module Stage2_Align (
  input  wire        clk,
  input  wire        rst,
  input  wire [23:0] A_man,
  input  wire [23:0] B_man,
  input  wire [7:0]  exp_diff,
  input  wire        A_bigger,
  input  wire [7:0]  A_exp,
  input  wire [7:0]  B_exp,

  output reg  [23:0] A_man_aligned,
  output reg  [23:0] B_man_aligned,
  output reg  [7:0]  exp_out
);
  always @(posedge clk or posedge rst) begin
    if (rst) begin
      {A_man_aligned,B_man_aligned,exp_out} <= 0;
    end else if (A_bigger) begin
      A_man_aligned <= A_man;
      B_man_aligned <= B_man >> exp_diff;
      exp_out       <= A_exp;
    end else begin
      A_man_aligned <= A_man >> exp_diff;
      B_man_aligned <= B_man;
      exp_out       <= B_exp;
    end
  end
endmodule

folder/FloatingCompare.v
// ================================
// Stage1_Compare (updated)
// ================================
module Stage1_Compare (
  input  wire         clk,
  input  wire         rst,
  input  wire [31:0]  A,
  input  wire [31:0]  B,
  input  wire         operation,   // 0→add, 1→subtract

  output reg          A_sign,
  output reg          B_sign,
  output reg          B_sign_eff,  // <-- effective B sign
  output reg  [7:0]   A_exp,
  output reg  [7:0]   B_exp,
  output reg  [23:0]  A_man,
  output reg  [23:0]  B_man,
  output reg  [7:0]   exp_diff,
  output reg          A_bigger
);
  always @(posedge clk or posedge rst) begin
    if (rst) begin
      {A_sign,B_sign_eff,A_exp,B_exp,A_man,B_man,exp_diff,A_bigger} <= 0;
    end else begin
      
      // raw extraction
      A_sign <= A[31];
      B_sign <= B[31];
      B_sign_eff <= B_sign ^ operation; // <-- XOR in the operation bit
      A_exp  <= A[30:23];
      B_exp  <= B[30:23];
      // build mantissas
      A_man  <= (A[30:23]==0) ? {1'b0, A[22:0]} : {1'b1, A[22:0]}; //implicit leading 1 for normalized , 0 for denormalized
      B_man  <= (B[30:23]==0) ? {1'b0, B[22:0]} : {1'b1, B[22:0]};
      // exponent diff and bigger flag
      if (A[30:23] >= B[30:23]) begin
        exp_diff  <= A[30:23] - B[30:23];
        A_bigger  <= 1;
      end else begin
        exp_diff  <= B[30:23] - A[30:23];
        A_bigger  <= 0;
      end
    end
  end
endmodule

folder/PipelinedFAdd.v
module PipelinedFAdd (
  input  wire        clk,
  input  wire        rst,
  input  wire [31:0] A,
  input  wire [31:0] B,
  input  wire        operation,  // not used until Stage 3 if you prefer, but we embedded sign logic there

  output wire [31:0] result
);
  // Stage 1
  wire        A_sign1, B_sign1, A_bigger1;
  wire [7:0]  A_exp1, B_exp1, diff1;
  wire [23:0] A_man1, B_man1;


    Stage1_Compare U1 (
    .clk(clk),
    .rst(rst),
    .A(A),
    .B(B),
    .operation(operation),
    .A_sign(A_sign1),
    .B_sign_eff(B_sign1_eff),
    .A_exp(A_exp1),
    .B_exp(B_exp1),
    .A_man(A_man1),
    .B_man(B_man1),
    .exp_diff(diff1),
    .A_bigger(A_bigger1)
    );

  // Stage 2
  wire [23:0] A_man2, B_man2;
  wire [7:0]  exp2;

  Stage2_Align   U2(
    clk,
    rst,
    A_man1,
    B_man1,
    diff1,
    A_bigger1,
    A_exp1,
    B_exp1,
    A_man2,
    B_man2,
    exp2
    );

  // Stage 3
  wire [24:0] sum3;
  wire        sum_sign3;

    Stage3_Adder U3 (
    .clk(clk),
    .rst(rst),
    .A_man_aligned(A_man2),
    .B_man_aligned(B_man2),
    .A_sign(A_sign1),
    .B_sign_eff(B_sign1_eff),
    .sum_man(sum3),
    .sum_sign(sum_sign3)
    );
  // Stage 4
  Stage4_Normalize U4(clk,
    rst,
    sum3,
    exp2,
    sum_sign3,
    result
    );

endmodule

folder/tb_PipelinedFAdd.v
`timescale 1ns/1ps

module tb_PipelinedFAdd();

    reg clk = 0;
    reg reset = 1;
    reg [31:0] A, B;
    reg operation; // 0: Add, 1: Sub

    wire [31:0] result;

    PipelinedFAdd dut (
        .clk(clk),
        .rst(rst),
        .A(A),
        .B(B),
        .operation(operation),
        .result(result)
    );

    // Clock generation
    always #5 clk = ~clk;

        initial begin

            $monitor("Time: %0t | A: %h | B: %h | Op: %b | Result: %h", $time, A, B, operation, result);
            $dumpfile("build/waveform.vcd");
            $dumpvars(0, tb_PipelinedFAdd);
            

        #10 reset = 0;

        // Test 1: 13.65 + 10.2555 = 23.9055
        A = 32'h415a6666; // 13.65
        B = 32'h41241687; // 10.2555
        operation = 0;
        #50;

        // Test 2: 13.65 - 10.2555 = 3.3945
        A = 32'h415a6666; // 13.65
        B = 32'h41241687; // 10.2555
        operation = 1;
        #50;
        //Test 3: -13.65 + 10.2555 = -3.3945
        A = 32'hc15a6666; // -13.65
        B = 32'h41241687; // 10.2555
        operation = 0;
        #50;
        // Test 4: -13.65 - 10.2555 = -23.9055
        A = 32'hc15a6666; // -13.65
        B = 32'h41241687; // 10.2555
        operation = 1;
        #50;

        $finish;
    end

endmodule

build/waveform.vcd
$date
	Mon Jun  9 01:13:44 2025
$end
$version
	Icarus Verilog
$end
$timescale
	1ps
$end
$scope module tb_PipelinedFAdd $end
$var wire 1 ! rst $end
$var wire 32 " result [31:0] $end
$var reg 32 # A [31:0] $end
$var reg 32 $ B [31:0] $end
$var reg 1 % clk $end
$var reg 1 & operation $end
$var reg 1 ' reset $end
$scope module dut $end
$var wire 32 ( A [31:0] $end
$var wire 32 ) B [31:0] $end
$var wire 1 % clk $end
$var wire 1 & operation $end
$var wire 1 ! rst $end
$var wire 1 * sum_sign3 $end
$var wire 25 + sum3 [24:0] $end
$var wire 32 , result [31:0] $end
$var wire 8 - exp2 [7:0] $end
$var wire 8 . diff1 [7:0] $end
$var wire 1 / B_sign1_eff $end
$var wire 24 0 B_man2 [23:0] $end
$var wire 24 1 B_man1 [23:0] $end
$var wire 8 2 B_exp1 [7:0] $end
$var wire 1 3 A_sign1 $end
$var wire 24 4 A_man2 [23:0] $end
$var wire 24 5 A_man1 [23:0] $end
$var wire 8 6 A_exp1 [7:0] $end
$var wire 1 7 A_bigger1 $end
$scope module U1 $end
$var wire 32 8 A [31:0] $end
$var wire 32 9 B [31:0] $end
$var wire 1 % clk $end
$var wire 1 & operation $end
$var wire 1 ! rst $end
$var reg 1 7 A_bigger $end
$var reg 8 : A_exp [7:0] $end
$var reg 24 ; A_man [23:0] $end
$var reg 1 3 A_sign $end
$var reg 8 < B_exp [7:0] $end
$var reg 24 = B_man [23:0] $end
$var reg 1 > B_sign $end
$var reg 1 / B_sign_eff $end
$var reg 8 ? exp_diff [7:0] $end
$upscope $end
$scope module U2 $end
$var wire 1 7 A_bigger $end
$var wire 8 @ A_exp [7:0] $end
$var wire 24 A A_man [23:0] $end
$var wire 8 B B_exp [7:0] $end
$var wire 24 C B_man [23:0] $end
$var wire 1 % clk $end
$var wire 8 D exp_diff [7:0] $end
$var wire 1 ! rst $end
$var reg 24 E A_man_aligned [23:0] $end
$var reg 24 F B_man_aligned [23:0] $end
$var reg 8 G exp_out [7:0] $end
$upscope $end
$scope module U3 $end
$var wire 24 H A_man_aligned [23:0] $end
$var wire 1 3 A_sign $end
$var wire 24 I B_man_aligned [23:0] $end
$var wire 1 / B_sign_eff $end
$var wire 1 % clk $end
$var wire 1 ! rst $end
$var wire 1 J same_sign $end
$var reg 25 K sum_man [24:0] $end
$var reg 1 * sum_sign $end
$var reg 25 L temp_result [24:0] $end
$upscope $end
$scope module U4 $end
$var wire 1 % clk $end
$var wire 8 M exp_in [7:0] $end
$var wire 1 ! rst $end
$var wire 25 N sum_man [24:0] $end
$var wire 1 * sum_sign $end
$var reg 8 O exp_adj [7:0] $end
$var reg 24 P norm_man [23:0] $end
$var reg 32 Q result [31:0] $end
$var reg 5 R shift [4:0] $end
$scope function leading_zeros $end
$var reg 24 S val [23:0] $end
$var integer 32 T i [31:0] $end
$upscope $end
$upscope $end
$upscope $end
$upscope $end
$enddefinitions $end
#0
$dumpvars
bx T
bx S
bx R
bx Q
bx P
bx O
bx N
bx M
bx L
bx K
xJ
bx I
bx H
bx G
bx F
bx E
bx D
bx C
bx B
bx A
bx @
bx ?
x>
bx =
bx <
bx ;
bx :
bx 9
bx 8
x7
bx 6
bx 5
bx 4
x3
bx 2
bx 1
bx 0
x/
bx .
bx -
bx ,
bx +
x*
bx )
bx (
1'
x&
0%
bx $
bx #
bx "
z!
$end
#5000
07
b0 R
b11111111111111111111111111111111 T
1%
#10000
0%
0&
b1000001001001000001011010000111 $
b1000001001001000001011010000111 )
b1000001001001000001011010000111 9
b1000001010110100110011001100110 #
b1000001010110100110011001100110 (
b1000001010110100110011001100110 8
0'
#15000
17
b0 .
b0 ?
b0 D
b101001000001011010000111 1
b101001000001011010000111 =
b101001000001011010000111 C
b110110100110011001100110 5
b110110100110011001100110 ;
b110110100110011001100110 A
b10000010 2
b10000010 <
b10000010 B
b10000010 6
b10000010 :
b10000010 @
0>
03
b11111111111111111111111111111111 T
1%
#20000
0%
#25000
1J
0/
b10000010 -
b10000010 G
b10000010 M
b101001000001011010000111 0
b101001000001011010000111 F
b101001000001011010000111 I
b110110100110011001100110 4
b110110100110011001100110 E
b110110100110011001100110 H
b11111111111111111111111111111111 T
1%
#30000
0%
#35000
bx10000010xxxxxxxxxxxxxxxxxxxxxxx "
bx10000010xxxxxxxxxxxxxxxxxxxxxxx ,
bx10000010xxxxxxxxxxxxxxxxxxxxxxx Q
0*
b1011111100111110011101101 L
b10000010 O
b11111111111111111111111111111111 T
1%
#40000
0%
#45000
b1011111100111110011101101 +
b1011111100111110011101101 K
b1011111100111110011101101 N
b10000010xxxxxxxxxxxxxxxxxxxxxxx "
b10000010xxxxxxxxxxxxxxxxxxxxxxx ,
b10000010xxxxxxxxxxxxxxxxxxxxxxx Q
b11111111111111111111111111111111 T
1%
#50000
0%
#55000
b1000001101111110011111001110110 "
b1000001101111110011111001110110 ,
b1000001101111110011111001110110 Q
b101111110011111001110110 P
b10000011 O
1%
#60000
0%
1&
#65000
0J
1/
1%
#70000
0%
#75000
b1101100100111111011111 L
1%
#80000
0%
#85000
b1101100100111111011111 +
b1101100100111111011111 K
b1101100100111111011111 N
1%
#90000
0%
#95000
b1000000010110010011111101111100 "
b1000000010110010011111101111100 ,
b1000000010110010011111101111100 Q
b110110010011111101111100 P
b10000000 O
b10 R
b11111111111111111111111111111110 T
b1101100100111111011111 S
1%
#100000
0%
#105000
b11111111111111111111111111111110 T
1%
#110000
0%
0&
b11000001010110100110011001100110 #
b11000001010110100110011001100110 (
b11000001010110100110011001100110 8
#115000
0/
13
b11111111111111111111111111111110 T
1%
#120000
0%
#125000
1*
b11111111111111111111111111111110 T
1%
#130000
0%
#135000
b11000000010110010011111101111100 "
b11000000010110010011111101111100 ,
b11000000010110010011111101111100 Q
b11111111111111111111111111111110 T
1%
#140000
0%
#145000
b11111111111111111111111111111110 T
1%
#150000
0%
#155000
b11111111111111111111111111111110 T
1%
#160000
0%
1&
#165000
1J
1/
b11111111111111111111111111111110 T
1%
#170000
0%
#175000
b1011111100111110011101101 L
b11111111111111111111111111111110 T
1%
#180000
0%
#185000
b1011111100111110011101101 +
b1011111100111110011101101 K
b1011111100111110011101101 N
b11111111111111111111111111111110 T
1%
#190000
0%
#195000
b11000001101111110011111001110110 "
b11000001101111110011111001110110 ,
b11000001101111110011111001110110 Q
b101111110011111001110110 P
b10000011 O
1%
